tspec/__init__.py
tspec/core.py
tspec-0.0.2.dist-info/METADATA
tspec-0.0.2.dist-info/WHEEL
tspec-0.0.2.dist-info/entry_points.txt
tspec-0.0.2.dist-info/license_files/LICENSE
tspec-0.0.2.dist-info/RECORD
