Metadata-Version: 2.1
Name: tspec
Version: 0.0.2
Summary: Tspec Python package (alpha - work in progess)
Project-URL: Bug Tracker, https://github.com/tspec/lib-py/issues
Project-URL: Homepage, https://github.com/tspec/lib-py
Author-email: Ziya Suzen <mtmk@suzen.net>, Sri Sri <cos.itroot@gmail.com>
License: MIT License
Classifier: License :: OSI Approved :: MIT License
Classifier: Operating System :: OS Independent
Classifier: Programming Language :: Python :: 3
Requires-Python: >=3.7
